[
  {
    "name": "Humla",
    "flower": "Gullviva",
    "animal": "Hasselmus",
    "id": 1.3701936349308559
  },
  {
    "name": "Hummer",
    "flower": "Gullviva",
    "animal": "Hasselmus",
    "id": 1.0319897299934493
  },
  {
    "name": "Hatt",
    "flower": "Gullviva",
    "animal": "Hasselmus",
    "id": 0.9162667707977143
  },
  {
    "name": "Hand",
    "flower": "Gullviva",
    "animal": "Hasselmus",
    "id": 0.27210891317002917
  },
  {
    "name": "Hund",
    "flower": "Gullviva",
    "animal": "Hasselmus",
    "id": 0.8947119995975703
  }
]